{"message":"API with list of entity by user ","data":[{"id":1,"first_name":"Kathirmalan","last_name":"Shanmugam","age":29,"entity":[{"entity_name":"UI\/UX developer","entity_department":"Software Development"},{"entity_name":"Backend Developer","entity_department":"Software Development"}]},{"id":2,"first_name":"Thomas","last_name":"Igor","age":32,"entity":[{"entity_name":"Backend Developer","entity_department":"Software Development"}]},{"id":3,"first_name":"Alex","last_name":"Parker","age":33,"entity":[{"entity_name":"Backend Developer","entity_department":"Software Development"},{"entity_name":"Quality Analyst","entity_department":"Testing"}]},{"id":4,"first_name":"Mathew","last_name":"williams","age":33,"entity":[{"entity_name":"Backend Developer","entity_department":"Software Development"},{"entity_name":"Quality Analyst","entity_department":"Testing"}]}]}